CONTRIBUTORS.rst
LICENSE
MANIFEST.in
README.rst
requirements.txt
setup.cfg
setup.py
django_numpy/__init__.py
django_numpy/__init__.pyc
django_numpy/apps.py
django_numpy/fields.py
django_numpy/settings.py
django_numpy.egg-info/PKG-INFO
django_numpy.egg-info/SOURCES.txt
django_numpy.egg-info/dependency_links.txt
django_numpy.egg-info/not-zip-safe
django_numpy.egg-info/requires.txt
django_numpy.egg-info/top_level.txt