Metadata-Version: 1.1
Name: django-numpy
Version: 1.0.1
Summary: Application for Django projects that adds some utilities and integration tools with Numpy.
Home-page: https://github.com/PeRDy/django-numpy
Author: José Antonio Perdiguero López
Author-email: perdy.hh@gmail.com
License: GPLv3
Download-URL: https://github.com/PeRDy/django-numpy
Keywords: python django database numpy
Platform: UNKNOWN
Classifier: Development Status :: 5 - Production/Stable
Classifier: Framework :: Django
Classifier: Intended Audience :: Developers
Classifier: License :: OSI Approved :: GNU General Public License v3 (GPLv3)
Classifier: Natural Language :: English
Classifier: Programming Language :: Python
Classifier: Programming Language :: Python :: 2
Classifier: Programming Language :: Python :: 3
Classifier: Topic :: Software Development :: Libraries :: Python Modules
